[{"VareNr":213,"Pris":321,"Navn":"hmm","Kategori":0},{"VareNr":215,"Pris":87,"Navn":"g","Kategori":0},{"VareNr":9,"Pris":89,"Navn":"qq","Kategori":1},{"VareNr":1,"Pris":22,"Navn":"ikk","Kategori":1},{"VareNr":3,"Pris":21,"Navn":"wda","Kategori":2},{"VareNr":214,"Pris":321,"Navn":"sakd","Kategori":2},{"VareNr":9,"Pris":99,"Navn":"asjdj","Kategori":3},{"VareNr":216,"Pris":87,"Navn":"f","Kategori":3},{"VareNr":189,"Pris":213,"Navn":"ewpl","Kategori":4},{"VareNr":22,"Pris":32,"Navn":"fffffffff","Kategori":4},{"VareNr":99,"Pris":675,"Navn":"testM","Kategori":4}]